MANIFEST.in
README.md
requirements.txt
setup.py
src/pii_manager/__init__.py
src/pii_manager/piientity.py
src/pii_manager/piienum.py
src/pii_manager.egg-info/PKG-INFO
src/pii_manager.egg-info/SOURCES.txt
src/pii_manager.egg-info/dependency_links.txt
src/pii_manager.egg-info/entry_points.txt
src/pii_manager.egg-info/requires.txt
src/pii_manager.egg-info/top_level.txt
src/pii_manager/api/__init__.py
src/pii_manager/api/file.py
src/pii_manager/api/manager.py
src/pii_manager/app/__init__.py
src/pii_manager/app/manage.py
src/pii_manager/app/task_info.py
src/pii_manager/helper/__init__.py
src/pii_manager/helper/base.py
src/pii_manager/helper/context.py
src/pii_manager/helper/exception.py
src/pii_manager/helper/json.py
src/pii_manager/helper/normalizer.py
src/pii_manager/helper/taskdict.py
src/pii_manager/helper/types.py
src/pii_manager/lang/__init__.py
src/pii_manager/lang/any/__init__.py
src/pii_manager/lang/any/bitcoin_address.py
src/pii_manager/lang/any/credit_card.py
src/pii_manager/lang/any/email.py
src/pii_manager/lang/any/ip_address.py
src/pii_manager/lang/any/toy_example.py
src/pii_manager/lang/en/__init__.py
src/pii_manager/lang/en/any/__init__.py
src/pii_manager/lang/en/any/international_phone_number.py
src/pii_manager/lang/en/au/__init__.py
src/pii_manager/lang/en/au/abn.py
src/pii_manager/lang/en/au/tfn.py
src/pii_manager/lang/en/ca/__init__.py
src/pii_manager/lang/en/ca/social_insurance_number.py
src/pii_manager/lang/en/in_/__init__.py
src/pii_manager/lang/en/in_/aadhaar.py
src/pii_manager/lang/en/us/__init__.py
src/pii_manager/lang/en/us/social_security_number.py
src/pii_manager/lang/es/__init__.py
src/pii_manager/lang/es/any/__init__.py
src/pii_manager/lang/es/any/international_phone_number.py
src/pii_manager/lang/es/es/__init__.py
src/pii_manager/lang/es/es/bank_account.py
src/pii_manager/lang/es/es/govid.py
src/pii_manager/lang/es/mx/__init__.py
src/pii_manager/lang/es/mx/curp.py
src/pii_manager/lang/fr/__init__.py
src/pii_manager/lang/fr/ca/__init__.py
src/pii_manager/lang/fr/ca/social_insurance_number.py
src/pii_manager/lang/pt/__init__.py
src/pii_manager/lang/pt/br/__init__.py
src/pii_manager/lang/pt/br/cpf.py
src/pii_manager/lang/pt/pt/__init__.py
src/pii_manager/lang/pt/pt/govid.py
