Metadata-Version: 2.1
Name: pii-manager
Version: 0.5.0
Summary: Text Anonymization of PII
Home-page: https://github.com/bigscience-workshop/pii-manager
Author: Paulo Villegas
Author-email: paulo.vllgs@gmail.com
License: Apache
Download-URL: https://github.com/bigscience-workshop/pii-manager/tarball/v0.5.0
Keywords: Big Science Workshop, PII
Platform: UNKNOWN
Classifier: Programming Language :: Python :: 3 :: Only
Classifier: License :: OSI Approved :: Apache Software License
Classifier: Development Status :: 4 - Beta
Classifier: Topic :: Software Development :: Libraries :: Application Frameworks
Requires-Python: >=3.8
Provides-Extra: test
